mars_insight/__init__.py
mars_insight/api.py
mars_insight/models.py
mars_insight/plot.py
mars_insight-0.1.0.dist-info/LICENSE
mars_insight-0.1.0.dist-info/METADATA
mars_insight-0.1.0.dist-info/WHEEL
mars_insight-0.1.0.dist-info/top_level.txt
mars_insight-0.1.0.dist-info/RECORD
