Metadata-Version: 2.1
Name: mars-insight
Version: 0.1.0
Summary: Mars InSight weather service API client
Home-page: https://github.com/albertwigmore/mars-insight
Author: Albert Wigmore
Author-email: albertwigmore@googlemail.com
License: MIT
Platform: UNKNOWN
Classifier: Development Status :: 4 - Beta
Classifier: Intended Audience :: Developers
Classifier: Intended Audience :: Science/Research
Classifier: Operating System :: OS Independent
Classifier: Programming Language :: Python
Classifier: Programming Language :: Python :: 3.5
Classifier: Programming Language :: Python :: 3.6
Classifier: Programming Language :: Python :: 3.7
Classifier: Topic :: Scientific/Engineering
Classifier: Topic :: Software Development :: Libraries
Classifier: Topic :: Software Development :: Libraries :: Python Modules
Requires-Python: >=3.5
Requires-Dist: matplotlib
Requires-Dist: numpy
Requires-Dist: requests
Provides-Extra: dev
Requires-Dist: bandit ; extra == 'dev'
Requires-Dist: flake8 ; extra == 'dev'
Requires-Dist: nox ; extra == 'dev'
Requires-Dist: pylint ; extra == 'dev'
Requires-Dist: pytest ; extra == 'dev'
Requires-Dist: pytest-cov ; extra == 'dev'
Requires-Dist: sphinx ; extra == 'dev'
Requires-Dist: sphinx-press-theme ; extra == 'dev'
